{"_id":"23b357a0-ae64-11ea-b8ee-137063cd7f07","trap":"","parent":"","message":"Slots of Vegas Naughty Or Nice III 250% Bonus plus 30 FREE Spins New Game Promo \r\n<a href=https://norskecasinofor.com>Norges Casino рџҐ‡Norges Online Casino Guide</a> \r\n$10 Free chips bonus Grande vegas casino \r\n<a href=https://oncasslotreal.com>Online Casinos in - Top 3 Casinos for Blackjack, Craps or Slots</a> \r\nCasino King - tratamento VIP e bГґnus de $300 \r\n<a href=https://realcasinomachines.com>Top 10 Real Money Online Casinos () | Real Money Slots & Roulette</a> \r\nBest Г…land Online Casinos - Г…land Casino Bonuses \r\n<a href=https://aurealcasino.com>Online casinos</a> \r\nRoyal Panda Testbericht +++ Der Casino Test 2020 \r\n<a href=https://beonlinecasinoslots.com>Online Casino Spelen - Top Casino</a> \r\nGowild Casino 25 free spins bonus \r\n<a href=https://bestenonlinecasinosde.com>Online casino de</a> \r\nBook Of The Sphinx Slots Review - Online Slots \r\n<a href=https://dkcasinospil.com>Casino Online рџҐ‡ Unik oversigt med de bedste online casinoer</a> \r\nBetclic: European Club bringt 5 Euro Wochenend-Bonus \r\n<a href=https://finnettikasinot.com>Nettikasino Top - Parhaat Suomalaiset Nettikasinot</a> \r\nMore Information on Golden Winnings \r\n<a href=https://franceslotcas.com>Roulette</a> \r\n50в‚¬ No deposit bonus at Lota Play Casino \r\n<a href=https://frslotsenligne.com>Roulette</a> \r\nFootball Rules Slot Machine Online в–· Play FREE Football Rules Game","name":"Bryandah","email":"e305eee05be40670cb9c9def01aed675","website":"","date":"2020-06-14T17:26:11.034Z"}