{"_id":"9ee3a840-1be6-11eb-81b4-756c49ffc65e","trap":"","parent":"","message":"加入这里make钱的成功人士的社会。 \r\n链接 - http://www.google.com/url?q=%68%74%74%70%73%3A%2F%2F%68%64%72%65%64%74%75%62%65%33%2e%6d%6f%62%69%2F%62%74%73%6d%61%72%74%23%76%6e%77%44%68%4f%75%6a%51%55%6a%6e%44%49%68%47%6f&sa=D&sntz=1&usg=AFQjCNGT-HhoPhmp5k-UyfYSjcxvZyZGcA","name":"HenryPut","email":"817e3013ed84ad9edc4aac317a385f7a","website":"http://www.google.com/url?q=%68%74%74%70%73%3A%2F%2F%68%64%72%65%64%74%75%62%65%33%2e%6d%6f%62%69%2F%62%74%73%6d%61%72%74%23%77%48%65%62%65%77%67%72%69%47%4e%7a%67%77%45%4b%75&sa=D&sntz=1&usg=AFQjCNFYSidZ1MBnbA1LQIQ2t2HwQWjQwg","date":"2020-11-01T02:04:48.943Z"}