{"_id":"32672940-ad72-11ea-8cb6-0fc149f21e33","trap":"","parent":"","message":"СѓР·РЅР°Р№ СЃРѕРІРµС‚:  \r\n<a href=https://kok7.ru/poisk.php?q=kak-vybrat'-prichesku-zhenshhine-po-forme-lica>РєР°Рє РІС‹Р±СЂР°С‚СЊ РїСЂРёС‡РµСЃРєСѓ Р¶РµРЅС‰РёРЅРµ РїРѕ С„РѕСЂРјРµ Р»РёС†Р°</a>\r\n<a href=https://krasota.info-sovety.ru/poisk.php?q=kak-vybrat'-obuv'-na-alijekspress>РєР°Рє РІС‹Р±СЂР°С‚СЊ РѕР±СѓРІСЊ РЅР° Р°Р»РёСЌРєСЃРїСЂРµСЃСЃ</a>\r\n<a href=https://avto.man-das.ru/poisk.php?q=kak-vybrat'-rabotu-po-dushe>РєР°Рє РІС‹Р±СЂР°С‚СЊ СЂР°Р±РѕС‚Сѓ РїРѕ РґСѓС€Рµ</a>\r\n<a href=https://finansy.info-sovety.ru/poisk.php?q=kak-vybrat'-kvartiru-dlja-pokupki>РєР°Рє РІС‹Р±СЂР°С‚СЊ РєРІР°СЂС‚РёСЂСѓ РґР»СЏ РїРѕРєСѓРїРєРё</a>\r\n<a href=https://man-das.ru/poisk.php?q=kak-vybrat'-stil'-v-odezhde-devushke>РєР°Рє РІС‹Р±СЂР°С‚СЊ СЃС‚РёР»СЊ РІ РѕРґРµР¶РґРµ РґРµРІСѓС€РєРµ</a>\r\n \r\n<a href=https://female-ru.ru/video/ziXX-4TYpuE>10 РїРѕР»РµР·РЅС‹С… СЃРѕРІРµС‚РѕРІ РЅР° РєР°Р¶РґС‹Р№ РґРµРЅСЊ. РЎРѕРІРµС‚С‹ РЅР° РІСЃРµ СЃР»СѓС‡Р°Рё РІ Р¶РёР·РЅРё</a>","name":"Valeti dag","email":"42ddbbb26eba332872a775d0e8e6a4f2","website":"","date":"2020-06-13T12:34:17.414Z"}