{"_id":"47d65100-0b02-11eb-a51c-716589f5f9f0","trap":"","parent":"","message":"<a href=http://voprosy.by/search?q=Новосибирск купить закладку Кокаин, Мефедрон, Амфетамин, Гашиш, Скорость (Ск Альфа-ПВП), Марихуана, Экстази заходи на сайт - INRUS.TOP >закладка купить</a><a href=https://vladnews.ru/search?q=Пермь купить закладку Кокаин, Мефедрон, Амфетамин, Гашиш, Скорость (Ск Альфа-ПВП), Марихуана, Экстази заходи на сайт - INRUS.TOP >закладка купить</a><a href=https://jobs.bnsf.com/search/?q=Красноярск купить закладку Кокаин, Мефедрон, Амфетамин, Гашиш, Скорость (Ск Альфа-ПВП), Марихуана, Экстази заходи на сайт - INRUS.TOP >закладка купить</a><a href=https://www.panram.ru/tags/Волгоград купить закладку Кокаин, Мефедрон, Амфетамин, Гашиш, Скорость (Ск Альфа-ПВП), Марихуана, Экстази заходи на сайт - INRUS.TOP >закладка купить</a><a href=https://www.otzywy.com/Москва/search/?what=Кемерово купить закладку Кокаин, Мефедрон, Амфетамин, Гашиш, Скорость (Ск Альфа-ПВП), Марихуана, Экстази заходи на сайт - INRUS.TOP >закладка купить</a><a href=https://www.business-gazeta.ru/search/Новосибирск купить закладку Кокаин, Мефедрон, Амфетамин, Гашиш, Скорость (Ск Альфа-ПВП), Марихуана, Экстази заходи на сайт - INRUS.TOP >закладка купить</a><a href=https://www.bragazeta.ru/?s=Тула | Курск купить закладку Кокаин, Мефедрон, Амфетамин, Гашиш, Скорость (Ск Альфа-ПВП), Марихуана, Экстази заходи на сайт - INRUS.TOP >закладка купить</a><a href=http://brupress.ru/?s=Екатеринбург купить закладку Кокаин, Мефедрон, Амфетамин, Гашиш, Скорость (Ск Альфа-ПВП), Марихуана, Экстази заходи на сайт - INRUS.TOP >закладка купить</a><a href=http://www.panram.ru/tags/Оренбург купить закладку Кокаин, Мефедрон, Амфетамин, Гашиш, Скорость (Ск Альфа-ПВП), Марихуана, Экстази заходи на сайт - INRUS.TOP >закладка купить</a><a href=https://happygamer.com/?s=Челябинск купить закладку Кокаин, Мефедрон, Амфетамин, Гашиш, Скорость (Ск Альфа-ПВП), Марихуана, Экстази заходи на сайт - INRUS.TOP >закладка купить</a><a href=https://www.newsnow.co.uk/h/?search=Набережные Челны купить закладку Кокаин, Мефедрон, Амфетамин, Гашиш, Скорость (Ск Альфа-ПВП), Марихуана, Экстази заходи на сайт - INRUS.TOP >закладка купить</a><a href=http://www.panram.ru/tags/Хабаровск купить закладку Кокаин, Мефедрон, Амфетамин, Гашиш, Скорость (Ск Альфа-ПВП), Марихуана, Экстази заходи на сайт - INRUS.TOP >закладка купить</a><a href=https://happygamer.com/?s=Барнаул купить закладку Кокаин, Мефедрон, Амфетамин, Гашиш, Скорость (Ск Альфа-ПВП), Марихуана, Экстази заходи на сайт - INRUS.TOP >закладка купить</a><a href=https://www.filippa-k.com/sv/sok?q=Омск купить закладку Кокаин, Мефедрон, Амфетамин, Гашиш, Скорость (Ск Альфа-ПВП), Марихуана, Экстази заходи на сайт - INRUS.TOP >закладка купить</a><a href=https://news.un.org/ru/search/Оренбург купить закладку Кокаин, Мефедрон, Амфетамин, Гашиш, Скорость (Ск Альфа-ПВП), Марихуана, Экстази заходи на сайт - INRUS.TOP >закладка купить</a><a href=http://primorye24.ru/news/search?q=Оренбург купить закладку Кокаин, Мефедрон, Амфетамин, Гашиш, Скорость (Ск Альфа-ПВП), Марихуана, Экстази заходи на сайт - INRUS.TOP >закладка купить</a><a href=http://voprosy.by/search?q=Пермь купить закладку Кокаин, Мефедрон, Амфетамин, Гашиш, Скорость (Ск Альфа-ПВП), Марихуана, Экстази заходи на сайт - INRUS.TOP >закладка купить</a><a href=http://primorye24.ru/news/search?q=Волгоград купить закладку Кокаин, Мефедрон, Амфетамин, Гашиш, Скорость (Ск Альфа-ПВП), Марихуана, Экстази заходи на сайт - INRUS.TOP >закладка купить</a><a href=http://brupress.ru/?s=Новокузнецк купить закладку Кокаин, Мефедрон, Амфетамин, Гашиш, Скорость (Ск Альфа-ПВП), Марихуана, Экстази заходи на сайт - INRUS.TOP >закладка купить</a><a href=https://happygamer.com/?s=Кемерово купить закладку Кокаин, Мефедрон, Амфетамин, Гашиш, Скорость (Ск Альфа-ПВП), Марихуана, Экстази заходи на сайт - INRUS.TOP >закладка купить</a>","name":"Kennethjouct","email":"0cd001be76ebfe82b8e5aa7cdf86bc3d","website":"","date":"2020-10-10T14:09:59.116Z"}