{"_id":"f5a41560-a95f-11ea-b7ee-713876424630","trap":"","parent":"","message":"Our company offers supreme quality health and related products. Look at our health contributing portal in case you want to feel better. <a href=https://ps2.medinfocode.com/modafinil/it/40989-modafinil-blog-70925.html>https://ps2.medinfocode.com/modafinil/it/40989-modafinil-blog-70925.html</a> Our company provides a wide variety of non prescription products. Look at our health website in case you want to look healthier  with a help of health products. <a href=https://hk23.medinfocode.com/modafinil/no/33904-modafinil-and-sex-8636.html>https://hk23.medinfocode.com/modafinil/no/33904-modafinil-and-sex-8636.html</a> Our company provides a wide variety of non prescription products. Take a look at our health website in case you want to to feel healthier with a help of health products. <a href=https://iw08.medinfocode.com/modafinil/es/58222-provigil-online-19887.html>https://iw08.medinfocode.com/modafinil/es/58222-provigil-online-19887.html</a> Our company provides healthcare products. Take a look at our health contributing portal in case you want to strengthen your health. <a href=https://f3.medinfocode.com/modafinil/es/76726-modafinil-how-to-take-93465.html>https://f3.medinfocode.com/modafinil/es/76726-modafinil-how-to-take-93465.html</a> Our company offers supreme quality supplements. Look at our health contributing portal in case you want to look better. https://q0.medinfocode.com/modafinil/pt/48231-modafinil-pakistan-42230.html Our company offers herbal non prescription products. Look at our health contributing site in case you want to strengthen your health. <a href=https://iw08.medinfocode.com/modafinil/nl/11231-provigil-150-mg-70746.html>https://iw08.medinfocode.com/modafinil/nl/11231-provigil-150-mg-70746.html</a> \r\nOur company provides a wide variety of non prescription products. Look at our health site in case you want to to improve your health with a help generic supplements. <a href=https://3di.medinfocode.com/modafinil/it/95054-provigil-and-wellbutrin-50283.html>https://3di.medinfocode.com/modafinil/it/95054-provigil-and-wellbutrin-50283.html</a> Our company provides a wide variety of non prescription products. Visit our health portal in case you want to to improve your health with a help of health products. <a href=https://6ph.medinfocode.com/modafinil/it/78907-provigil-heart-problems-4462.html>https://6ph.medinfocode.com/modafinil/it/78907-provigil-heart-problems-4462.html</a>  Our company provides herbal pharmacy. Look at our health contributing portal in case you want to look better. <a href=https://9i.medinfocode.com/modafinil/es/94395-modafinil-tab-38965.html>https://9i.medinfocode.com/modafinil/es/94395-modafinil-tab-38965.html</a> Our company provides a wide variety of non prescription products. Look at our health portal in case you want to feel better with a help generic supplements. https://3di.medinfocode.com/modafinil/en/31304-modalert-amazon-20153.html Our company provides herbal health products. Look at our health contributing site in case you want to look better.","name":"Philipgrify","email":"edbe3387b8bfd2ceb066affb560281f4","website":"https://1k.medinfocode.com","date":"2020-06-08T08:13:39.935Z"}