{"_id":"311f9580-71ba-11e9-a6c3-add47ff521ab","trap":"","parent":"","message":"dentro de ti\r\nkim sexy teen striptease\r\nseduced in massage room\r\nhung hairy body\r\nta que abusiva\r\nnot usual fake\r\nwe are so pleased\r\n \r\n \r\nhttp://www.carmenhotelfinance.com/\r\nhttp://www.panorama.lupef.se/lupefs-styrelse/\r\nhttp://www.ishangh.com/space-uid-399981.html\r\nhttp://associationscitoyennes.forumcrea.com/post.php?tid=9396\r\nhttp://www.ymygl.com.cn/bbs/home.php?mod=space&uid=116360\r\nhttp://www.online-einsaetze.de/forum/showthread.php?tid=1638899&pid=1911292#pid1911292\r\n \r\n \r\n<a href=https://www.gutgesell-bau.de/kontakt/>cum on white ress</a> \r\n<a href=https://blacknotes.noblogs.org/post/2015/01/11/charlie-1-4/#comment-22271>teen blonde small tit</a> \r\n<a href=http://www.350jhm.net/space-uid-4847.html>jennifer watkins xxx</a> \r\nfree fisting pics galleries\r\ntiffany teen 2007 pics\r\nmpegs free huge boobs\r\ntease xxx dvd","name":"alish","email":"ddda86a37177d449458675829dfc0b0b","website":"https://hg008808.info/","date":"2019-05-08T17:53:31.796Z"}