{"_id":"90ab0310-62e9-11ea-af0f-2b80f6e96fe2","trap":"","parent":"","message":"Hello! \r\nA dissertation or thesis is prepared under the supervision of a tutor or director. It is reviewed by a Doctoral Committee composed of examiners external to the program and at least one examiner external to the institution. The degree is conferred after a successful dissertation defence.\r\n \r\nhttp://social2people.org/socialnet/viewtopic.php?f=3&t=430355\r\n \r\n \r\nbuy essays cheap\r\nbuy essays for college","name":"StephenVok","email":"55aeca28b0cc47e7525e39f2637ecfff","website":"","date":"2020-03-10T16:09:48.704Z"}