{"_id":"bd9ff8b0-dd3e-11ea-a721-25f4dbcdc421","trap":"","parent":"","message":"https://amiro-service.ru/elektrostal.html \r\n<a href=https://baltles96.ru/portofino-italiya.html>Портофино Италия</a> \r\nhttps://afhc.ru \r\nhttp://terra-bashkiria.ru/forum/?PAGE_NAME=profile_view&UID=46283 \r\nhttp://www.bybynail.com/home.php?mod=space&uid=166626 \r\nhttps://kakrabota.ru/tallin-estoniya-1.html \r\n<a href=https://gardendacha.ru/muyne-vetnam.html>Муйне Вьетнам</a> \r\nhttps://ecoskm.ru \r\nhttp://vsobaka.ru/communication/forum/user/15090/ \r\nhttps://trashbox.biz/user/ElmerViard/ \r\nhttps://medicinemaska.ru/vilnyus.html \r\n<a href=https://arp-azs.ru/map17.html>Стокгольм</a> \r\nhttps://tech-bussines.ru \r\nhttp://bazarweb.ru/forum.php/?PAGE_NAME=profile_view&UID=1216 \r\nhttp://hamsafon.tj/user/PhilipExind/ \r\nhttps://kakrabota.ru/helsinki.html \r\n<a href=https://a-kafedra.ru/kemerovskaya-oblast.html>Кемеровская область</a> \r\nhttps://amiro-service.ru \r\nhttp://harmonyl.ru/forum/index.php?PAGE_NAME=profile_view&UID=62388 \r\nhttps://siege.gg/user/Johnnyker \r\nhttps://tkpetrovich.ru/kaunas-litva-1.html \r\n<a href=https://a-kafedra.ru/mekka-saudovskaya-araviya.html>Мекка Саудовская Аравия</a> \r\nhttps://aboutchild.ru \r\nhttp://test.sozapag.ru/forum/user/51210/ \r\nhttp://tsaijia.com/space-uid-1250262.html","name":"RobertAnges","email":"2a4c0d1427c2fa8c020f9bce2d91eb6a","website":"","date":"2020-08-13T08:26:53.012Z"}