{"_id":"00c5fa20-ef9d-11ea-8c51-bdb5022b8bb9","trap":"","parent":"","message":"hOur company offers a wide variety of non prescription products. Look at our health site in case you want to look better with a help general health products. <a href=https://ld4.modafinilbuynow.com/nl/kopen-provigil-qc-supply-9451.html>https://ld4.modafinilbuynow.com/nl/kopen-provigil-qc-supply-9451.html</a> Our company offers a wide variety of pharmacy. Visit our health contributing site in case you want to strengthen your health. <a href=https://6p.modafinilbuynow.com/sv/modafinil-kostnad-cq-magazine-72059.html>https://6p.modafinilbuynow.com/sv/modafinil-kostnad-cq-magazine-72059.html</a> Our company offers a wide variety of non prescription drugs. Visit our health site in case you want to strengthen your health with a help general health products. <a href=https://5u.modafinilbuynow.com/sv/modafinil-priser-eaa-2016-83295.html>https://5u.modafinilbuynow.com/sv/modafinil-priser-eaa-2016-83295.html</a> Our company offers a wide variety of weight loss products. Visit our health contributing portal in case you want to strengthen your health. <a href=https://f1d.modafinilbuynow.com/sv/bestaella-modafinil-mug-41445.html>https://f1d.modafinilbuynow.com/sv/bestaella-modafinil-mug-41445.html</a> Our company offers supreme quality general health products. Take a look at our health contributing site in case you want to feel better. https://42zx.modafinilbuynow.com/de/provigil-now-available-online-76156.html Our company offers a wide variety of non prescription drugs. Look at our health site in case you want to to improve your health with a help of generic supplements. <a href=https://2iw8.modafinilbuynow.com/sv/modafinil-utan-recept-mh370-2018.html>https://2iw8.modafinilbuynow.com/sv/modafinil-utan-recept-mh370-2018.html</a> \r\nOur company provides healthcare products. Look at our health contributing website in case you want to look better. <a href=https://2ry.modafinilbuynow.com/fr/modafinil-en-ligne-kvitova-14206.html>https://2ry.modafinilbuynow.com/fr/modafinil-en-ligne-kvitova-14206.html</a> Our company offers a wide variety of non prescription products. Look at our health portal in case you want to strengthen your health with a help health products. <a href=https://7v.modafinilbuynow.com/nl/modafinil-zonder-recept-ferero-20729.html>https://7v.modafinilbuynow.com/nl/modafinil-zonder-recept-ferero-20729.html</a>  Our company offers a wide variety of non prescription products. Look at our health portal in case you want to to improve your health with a help of generic supplements. <a href=https://59yt.modafinilbuynow.com/nl/koop-provigil-crema-53083.html>https://59yt.modafinilbuynow.com/nl/koop-provigil-crema-53083.html</a> Our company provides generic supplements. Visit our health contributing portal in case you want to feel healthier. https://3k.modafinilbuynow.com/it/provigil-5-mg-prezzo-farmacia-87477.html Our company offers a wide variety of health and related products. Look at our health contributing website in case you want to look healthier.","name":"WilliamZen","email":"33d6c6342713624703820e0dbb8a328f","website":"https://3s.modafinilbuynow.com","date":"2020-09-05T17:26:59.324Z"}